{
    "$schema": "http://json-schema.org/draft-04/schema#",
    "type": "object",
    "properties": {
        "id": {
            "type": "string",
            "pattern": "DD[a-zA-Z0-9]{16,32}"
        },
        "href": {
            "type": "string",
            "format": "uri"
        },
        "created_at": {
            "type": "string",
            "format": "date-time"
        },
        "updated_at": {
            "type": "string",
            "format": "date-time"
        },
        "url": {
            "description": "The url where the file may be accessed",
            "type": "string",
            "format": "uri"
        },
        "mime_type": {
            "type": "string",
            "enum": [
                "application/pdf",
                "application/msword",
                "application/vnd.openxmlformats-officedocument.wordprocessingml.document",
                "image/jpeg"
            ]
        },
        "file_name": {
            "description": "Name of the document",
            "type": "string"
        },
        "file_size": {
            "description": "Size on disk of the document",
            "type": "integer"
        },
        "meta": {
            "$ref": "meta.json"
        },
        "links": {
            "type": "object",
            "properties": {
                "dispute": {
                    "description": "The dispute the customer has filed with their bank associated with this debit",
                    "type": [
                        "null",
                        "string"
                    ],
                    "pattern": "DT[a-zA-Z0-9]{16,32}"
                }
            },
            "additionalProperties": false,
            "required": [
                "dispute"
            ]
        }
    },
    "additionalProperties": false,
    "required": [
        "id",
        "href",
        "created_at",
        "updated_at",
        "url",
        "mime_type",
        "file_name",
        "file_size",
        "meta",
        "links"
    ]
}